{
    "answerArea": {
        "calculator": false,
        "chi2Table": false,
        "periodicTable": false,
        "tTable": false,
        "zTable": false
    },
    "hints": [
        {
            "content": "There are $\\blueE3$ rows with $\\purpleD3$ circles in each row.\n\n![](web+graphie://cdn.kastatic.org/ka-perseus-graphie/8a525cb0d0d53ccdfc8c6712ed213c5043235e02)",
            "images": {
                "web+graphie://cdn.kastatic.org/ka-perseus-graphie/8a525cb0d0d53ccdfc8c6712ed213c5043235e02": {
                    "height": 130,
                    "width": 130
                }
            },
            "replace": false,
            "widgets": {}
        },
        {
            "content": "$\\blueE3$ rows of $\\purpleD3$ is equal to $\\overset{\\blueE1}\\purpleD3+\\overset{\\blueE2}\\purpleD3 +\\overset{\\blueE3}\\purpleD3$.",
            "images": {},
            "replace": false,
            "widgets": {}
        },
        {
            "content": "The number of circles is equal to:  \n\n* $3+3+3$",
            "images": {},
            "replace": false,
            "widgets": {}
        }
    ],
    "itemDataVersion": {
        "major": 0,
        "minor": 1
    },
    "question": {
        "content": "**Which choice describes the number of circles?**\n\n![](web+graphie://cdn.kastatic.org/ka-perseus-graphie/20c928c40b1532e6b9fa1a7b1f18bbe4dc34deda)\n\n[[☃ radio 2]] ",
        "images": {
            "web+graphie://cdn.kastatic.org/ka-perseus-graphie/20c928c40b1532e6b9fa1a7b1f18bbe4dc34deda": {
                "height": 110,
                "width": 110
            }
        },
        "widgets": {
            "radio 2": {
                "alignment": "default",
                "graded": true,
                "options": {
                    "choices": [
                        {
                            "content": "$2+2+2+2$",
                            "correct": false
                        },
                        {
                            "content": "$3+3+3+3$",
                            "correct": false
                        },
                        {
                            "content": "$3+3+3$",
                            "correct": true
                        }
                    ],
                    "countChoices": true,
                    "deselectEnabled": false,
                    "displayCount": null,
                    "hasNoneOfTheAbove": false,
                    "multipleSelect": false,
                    "randomize": true
                },
                "static": false,
                "type": "radio",
                "version": {
                    "major": 1,
                    "minor": 0
                }
            }
        }
    }
}